Metadata-Version: 1.1
Name: cloudelements
Version: 0.2.1
Summary: SDK for Cloud Elements
Home-page: http://leadgenius.github.com/cloudelements
Author: LeadGenius
Author-email: developer@leadgenius.com
License: MIT
Platform: UNKNOWN
Classifier: Programming Language :: Python
